purechance/__init__.py
purechance/__main__.py
purechance/_cli_entry.py
purechance/cli.py
purechance/core.py
purechance-0.1.0rc3.dist-info/WHEEL
purechance-0.1.0rc3.dist-info/entry_points.txt
purechance-0.1.0rc3.dist-info/METADATA
purechance-0.1.0rc3.dist-info/RECORD
