Metadata-Version: 2.3
Name: purechance
Version: 0.1.0rc3
Summary: 
Author: oyghen
Author-email: oyghen <oyghen@duck.com>
Requires-Dist: typer>=0.20.1 ; extra == 'cli'
Requires-Python: >=3.11
Provides-Extra: cli
